tomlcheck/__init__.py
tomlcheck/main.py
tomlcheck/run.py
tomlcheck-0.2.3.dist-info/METADATA
tomlcheck-0.2.3.dist-info/WHEEL
tomlcheck-0.2.3.dist-info/entry_points.txt
tomlcheck-0.2.3.dist-info/RECORD
