Metadata-Version: 2.1
Name: tomlcheck
Version: 0.2.3
Summary: A simple toml syntax checker
Home-page: http://github.com/sayanarijit/tomlcheck
License: MIT
Keywords: toml,toml-validation,pre-commit,pre-commit-hooks
Author: Arijit Basu
Author-email: sayanarijit@gmail.com
Requires-Python: >=3.6,<4.0
Classifier: License :: OSI Approved :: MIT License
Classifier: Programming Language :: Python
Classifier: Programming Language :: Python :: 3
Classifier: Programming Language :: Python :: 3.6
Classifier: Programming Language :: Python :: 3.7
Classifier: Programming Language :: Python :: 3.8
Classifier: Programming Language :: Python :: 3.9
Classifier: Programming Language :: Python :: 3.10
Classifier: Programming Language :: Python :: 3.11
Classifier: Programming Language :: Python :: 3.12
Classifier: Topic :: Software Development
Requires-Dist: toml (>=0.10.0,<0.11.0)
Project-URL: Repository, http://github.com/sayanarijit/tomlcheck
